rtl/flipFlopNbit.v
//Copyright (C) 2018, Alexander Knapik
//Licensed under the GNU GPL v3.0 or any later version

module flipFlopNbit #(
		      parameter busWidth = 8 //Flip flop bus width. Default = 8 bits.
		    )
     (
      input [(busWidth - 1):0] D,
      input 			clk,
      input 			reset_n,
      output [(busWidth - 1):0] Q      
      );
   

  //Register for holding the output value. Used for assigning in an always block.
	reg [(busWidth - 1):0] q = 0;
   assign Q = q;
   
  
  always @(posedge(clk), negedge(reset_n)) begin
     //If the reset line is low, set the output to be zero despite the input.
     if(reset_n == 1'b0) begin
	q <= 0;
     end
     //Else if the reset line is low, and the flip flops are clocked, set the output
     //to equal the input.
     else if (clk == 1'b1) begin
	q <= D;
     end
     //Else, keep the output the same.
     else begin
	q <= q;
     end
  end//always
   
  endmodule // flipFlopNbit

rtl/flipFlopNbit_tb.v
module flipFlopNbit_tb;

   //Initial, default values.
   reg [7:0] D = 7'd0;
   reg 	     clk = 1'b0;
   reg 	     reset_n = 1'b0;
   wire [7:0] Q;

   initial
     begin
	//VCD dump file name
	$dumpfile("flipFlopNbit.vcd");
	//Set up the GTKWave axis titles
	$dumpvars(0, s);
	//Output text setup
	$monitor("D is %b, clk is %b, reset_n is %b, D is %b.", D, clk, reset_n, Q);


	//Setting each element at each time interval.
	//This must finish with $finish
   //Keep reset low for 20 periods.
   # 20 reset_n = 1;
   //Increment D every 50 periods
   # 50 D = 8'd1;
   # 50 D = 8'd2;
   # 50 D = 8'd3;
   # 50 D = 8'd4;
   # 50 D = 8'd5;
   # 50 D = 8'd6;
   # 50 D = 8'd7;
   # 50 D = 8'd10;
   # 50 D = 8'd20;
   # 50 D = 8'd200;
   # 50 reset_n = 0;
   # 200 $finish;
	
 	end // initial begin

   	//Make a clock signal for clk.
	always #5 clk = !clk;

   	flipFlopNbit s (D, clk, reset_n, Q);

endmodule // flipFlopNbit_tb

Simulation/flipFlopNbit.vcd
$date
	Sat Jun 23 16:08:52 2018
$end
$version
	Icarus Verilog
$end
$timescale
	1s
$end
$scope module flipFlopNbit_tb $end
$scope module s $end
$var wire 8 ! D [7:0] $end
$var wire 8 " Q [7:0] $end
$var wire 1 # clk $end
$var wire 1 $ reset_n $end
$var reg 8 % q [7:0] $end
$upscope $end
$upscope $end
$enddefinitions $end
#0
$dumpvars
b0 %
0$
0#
b0 "
b0 !
$end
#5
1#
#10
0#
#15
1#
#20
0#
1$
#25
1#
#30
0#
#35
1#
#40
0#
#45
1#
#50
0#
#55
1#
#60
0#
#65
1#
#70
0#
b1 !
#75
b1 "
b1 %
1#
#80
0#
#85
1#
#90
0#
#95
1#
#100
0#
#105
1#
#110
0#
#115
1#
#120
0#
b10 !
#125
b10 "
b10 %
1#
#130
0#
#135
1#
#140
0#
#145
1#
#150
0#
#155
1#
#160
0#
#165
1#
#170
0#
b11 !
#175
b11 "
b11 %
1#
#180
0#
#185
1#
#190
0#
#195
1#
#200
0#
#205
1#
#210
0#
#215
1#
#220
0#
b100 !
#225
b100 "
b100 %
1#
#230
0#
#235
1#
#240
0#
#245
1#
#250
0#
#255
1#
#260
0#
#265
1#
#270
0#
b101 !
#275
b101 "
b101 %
1#
#280
0#
#285
1#
#290
0#
#295
1#
#300
0#
#305
1#
#310
0#
#315
1#
#320
0#
b110 !
#325
b110 "
b110 %
1#
#330
0#
#335
1#
#340
0#
#345
1#
#350
0#
#355
1#
#360
0#
#365
1#
#370
0#
b111 !
#375
b111 "
b111 %
1#
#380
0#
#385
1#
#390
0#
#395
1#
#400
0#
#405
1#
#410
0#
#415
1#
#420
0#
b1010 !
#425
b1010 "
b1010 %
1#
#430
0#
#435
1#
#440
0#
#445
1#
#450
0#
#455
1#
#460
0#
#465
1#
#470
0#
b10100 !
#475
b10100 "
b10100 %
1#
#480
0#
#485
1#
#490
0#
#495
1#
#500
0#
#505
1#
#510
0#
#515
1#
#520
0#
b11001000 !
#525
b11001000 "
b11001000 %
1#
#530
0#
#535
1#
#540
0#
#545
1#
#550
0#
#555
1#
#560
0#
#565
1#
#570
b0 "
b0 %
0#
0$
