rtl/flipFlopNbit.v
//Copyright (C) 2018, Alexander Knapik
//Licensed under the GNU GPL v3.0 or any later version

module flipFlopNbit #(
		      parameter busWidth = 8 //Flip flop bus width. Default = 8 bits.
		    )
     (
      input [(busWidth - 1):0] D,
      input 			clk,
      input 			reset_n,
      output [(busWidth - 1):0] Q      
      );
   

  //Register for holding the output value. Used for assigning in an always block.
	reg [(busWidth - 1):0] q = 0;
   assign Q = q;
   
  
  always @(posedge(clk), negedge(reset_n)) begin
     //If the reset line is low, set the output to be zero despite the input.
     if(reset_n == 1'b0) begin
	q <= 0;
     end
     //Else if the reset line is low, and the flip flops are clocked, set the output
     //to equal the input.
     else if (clk == 1'b1) begin
	q <= D;
     end
     //Else, keep the output the same.
     else begin
	q <= q;
     end
  end//always
   
  endmodule // flipFlopNbit

rtl/ramController.v
//Copyright (C) 2018 Alexander Knapik
//Under the GNU General Public License v3.0 or any later version.

module ramController (
		      input [8:0]   Ain, //Input Address
		      input 	    OEin_n, //Input output Enable
		      input 	    CASU_n, //Input Column Address Strobe for upper byte
		      input 	    CASL_n, //Input Column Address Strobe for lower byte.
		      input 	    WE_n, //Input Write enable.
		      input 	    RAS_n, //Input Row Address Strobe.
		      output [17:0] Aout, //Output Address
		      output 	    OEout_n, //Output SRAM output enable
		      output 	    UB_n,
		      output 	    LB_n,
		      output 	    CE_n //Output SRAM chip enable.
		      );
   
   //Registers for assigning value in an always block.
   reg ce_n;
   assign CE_n = ce_n;
   
   reg lb_n;
   reg ub_n;
   assign LB_n = lb_n;
   assign UB_n = ub_n;

   reg [17:0] addressOut = 18'd0;
   assign Aout = addressOut;
      
   //For the Output Enable signal output, have it follow the input.
   //This is mainly for debugging to ensure that connecting it straight to the
   //RAM doesn't cause an issue further in the line after a PCB is made.
   assign OEout_n = OEin_n;
   
   //Instantiate two 9 bit flip flop arrays being used to latch the row and column addresses
   parameter busWidth = 9;

   //Wires used for connecting the Q values of the row and column latches to the IO pins
   //of the FPGA.
   wire [(busWidth - 1):0] rowAddress;
     
   //The reset lines are set to clear the latches once the various AS_n lines go high.
   //The clk is set to be the inverse of the varioud AS_n lines. 
    
   flipFlopNbit #(
		  busWidth
		  )
   rowLatch (
	     .D (Ain),
	     .clk (~RAS_n),
	     .reset_n (1'b1),
	     .Q (rowAddress)
	     );

   //If the RAS_n line goes low, set CE_n low.
   //This is so that once the RAS_n line goes low, this takes the RAM out of standby mode.
   always @(negedge(RAS_n)) begin
      if(RAS_n == 1'b0) begin
	 ce_n <= 1'b0;
      end
      else begin
	 ce_n <= 1'b1;
      end
   end //Always

   //If the CAS_n line goes low,
   //Set the output address to equal the rowAddress and the columnAddress wires.
   //Enable UB_n & LB_n depending on the CAS lines.
   always @(negedge(CASU_n), negedge(CASL_n)) begin
      if(CASU_n == 1'b0) begin
	 ub_n = 1'b0;
      end
      else begin
	 ub_n = 1'b1;
      end

      if(CASL_n == 1'b0) begin
	 lb_n = 1'b0;
      end
      else begin
	 lb_n = 1'b1;
      end
   end // always @ (negedge(CASU_n), negedge(CASL_n))
   
   always @(negedge(CASU_n), negedge(CASL_n)) begin
      addressOut [8:0] = rowAddress;
      addressOut [17:9] = Ain;
   end
   
   
 endmodule // ramController

rtl/ramController_tb.v
module ramController_tb;

   //Initial, default values.
   reg [8:0] 	Ain;
   reg	     	OEin_n;
   reg 	     	CASU_n;
   reg 		CASL_n;
   reg 		WE_n;
   reg 	   		RAS_n;
   wire [17:0] 		Aout;
   wire 		OEout_n;
   wire 		UB_n;
   wire        	LB_n;
   wire        	CE_n;
   
   initial begin
      //VCD dump file name
      $dumpfile("ramController.vcd");
      //Set up the GTKWave axis titles
      $dumpvars(0, s);
      //Output text setup
      // Use this as a print statement. Not being used as I will be using GTKWave instead.
      // $monitor("");
      
      //Setting each element at each time interval.
      //This must finish with $finish

      //FAST PAGE MODE READ CYCLE
      //-----------------------------------------------------------------------------------
      //FIRST CYCLE: READ FROM BOTH BYTES AT ADDRESS 0x134AF
      //SECOND CYCLE: READ FROM UPPER BYTE AT ADDRESS 0x144AF
      //THIRD CYCLE: RESD FROM LOWER BYTE AT ADDRESS 0x154AF

      //FIRST CYCLE:
      //Initial values. Set all addresses to zero, and all active low inputs high.
      #20 Ain = 8'd0;
      OEin_n = 1'b1;
      CASU_n = 1'b1;
      CASL_n = 1'b1;
      WE_n = 1'b1;
      RAS_n = 1'b1;
      //Set up an input address for reading a specific row index.
      #20 Ain = 9'h0af;
      //set RAS_n low.
      #10 RAS_n = 1'b0;
      //Set WE_n high, as its reading
      #10 WE_n = 1'b1;
      //Set which column index will be read from.
      #10 Ain = 9'h09a;
      //Set both CAS_n lines low. Reading 16 bits of data.
      #10 CASU_n = 1'b0;
      CASL_n = 1'b0;
      //Set the output enable low, as Dout will be active due to a read action.
      #10 OEin_n = 1'b0;
      #10 OEin_n = 1'b1;

      //SECOND CYCLE:
      //Set the CAS_n lines high to indicate that a new column address will be needed.
      //The 68000 will set the data input to high impendance. 
      #20 CASU_n = 1'b1;
      CASL_n = 1'b1;
      //Set WE_n low as once the column address is input, WE_n will be used as a rising edge.
      #10 WE_n = 1'b0;
      //Input the new 9 bit column address. 
      #10 Ain = 9'h09b;
      //Set WE_n to high as the DRAM would require a rising edge of WE_n.
      #10 WE_n = 1'b1;
      //Set CASU_n low to read from the upper byte of 0x144af
      #10 CASU_n = 1'b0;
      //Set the output enable low, allowing Dout to be active for a read cycle.
      #10 OEin_n = 1'b0;
      #10 OEin_n = 1'b1;
      
      //THIRD CYCLE:
      //Set the CAS_n lines high to indicate that a new column address will be needed.
      //The 68000 will set the data input to high impendance. 
      #20 CASU_n = 1'b1;
      CASL_n = 1'b1;
      //Set WE_n low as once the column address is input, WE_n will be used as a rising edge.
      #10 WE_n = 1'b0;
      //Input the new 9 bit column address. 
      #10 Ain = 9'h09c;
      //Set WE_n to high as the DRAM would require a rising edge of WE_n.
      #10 WE_n = 1'b1;
      //Set CASU_n low to read from the upper byte of 0x144af
      #10 CASU_n = 1'b0;
      //Set the output enable low, allowing Dout to be active for a read cycle.
      #10 OEin_n = 1'b0;

      //Set the RAM into standby.
      //Set the RAS_n line high.
      #10 RAS_n = 1'b1;
      //Set the output enable high.
      #10 OEin_n = 1'b1;
      //Set the CAS_n lines high. 
      #10 CASU_n = 1'b1;
      CASL_n = 1'b1;
      //Falling edge of write enable
      #10 WE_n = 1'b0;

      #50 $finish;
   end // initial

   ramController s(Ain, OEin_n, CASU_n, CASL_n, WE_n, RAS_n, Aout, OEout_n, UB_n, LB_n, CE_n);

endmodule // flipFlopNbit_tb

Simulation/ramController.vcd
$date
	Sun Jun 24 16:57:26 2018
$end
$version
	Icarus Verilog
$end
$timescale
	1s
$end
$scope module ramController_tb $end
$scope module s $end
$var wire 9 ! Ain [8:0] $end
$var wire 18 " Aout [17:0] $end
$var wire 1 # CASL_n $end
$var wire 1 $ CASU_n $end
$var wire 1 % CE_n $end
$var wire 1 & LB_n $end
$var wire 1 ' OEin_n $end
$var wire 1 ( OEout_n $end
$var wire 1 ) RAS_n $end
$var wire 1 * UB_n $end
$var wire 1 + WE_n $end
$var wire 9 , rowAddress [8:0] $end
$var reg 18 - addressOut [17:0] $end
$var reg 1 . ce_n $end
$var reg 1 / lb_n $end
$var reg 1 0 ub_n $end
$scope module rowLatch $end
$var wire 9 1 D [8:0] $end
$var wire 9 2 Q [8:0] $end
$var wire 1 3 clk $end
$var wire 1 4 reset_n $end
$var reg 9 5 q [8:0] $end
$upscope $end
$upscope $end
$upscope $end
$enddefinitions $end
#0
$dumpvars
b0 5
14
x3
b0 2
bx 1
x0
x/
x.
b0 -
b0 ,
x+
x*
x)
x(
x'
x&
x%
x$
x#
b0 "
bx !
$end
#20
03
1)
1+
1#
1$
1(
1'
b0 !
b0 1
#40
b10101111 !
b10101111 1
#50
b10101111 ,
b10101111 2
b10101111 5
0%
0.
13
0)
#70
b10011010 !
b10011010 1
#80
0&
0/
0*
00
b10011010010101111 "
b10011010010101111 -
0#
0$
#90
0(
0'
#100
1(
1'
#120
1#
1$
#130
0+
#140
b10011011 !
b10011011 1
#150
1+
#160
b10011011010101111 "
b10011011010101111 -
1&
1/
0$
#170
0(
0'
#180
1(
1'
#200
1$
#210
0+
#220
b10011100 !
b10011100 1
#230
1+
#240
b10011100010101111 "
b10011100010101111 -
0$
#250
0(
0'
#260
03
1)
#270
1(
1'
#280
1$
#290
0+
